dynamicforms/__init__.py
dynamicforms/action.py
dynamicforms/apps.py
dynamicforms/fields.py
dynamicforms/filters.py
dynamicforms/int_choice_enum.py
dynamicforms/models.py
dynamicforms/models_fields.py
dynamicforms/pagination.py
dynamicforms/preupload_files.py
dynamicforms/progress.py
dynamicforms/renderers.py
dynamicforms/routers.py
dynamicforms/serializers.py
dynamicforms/struct.py
dynamicforms/urls.py
dynamicforms/utils.py
dynamicforms/views.py
dynamicforms/viewsets.py
dynamicforms/locale/en/LC_MESSAGES/django.po
dynamicforms/locale/en/LC_MESSAGES/djangojs.po
dynamicforms/locale/sl/LC_MESSAGES/django.po
dynamicforms/locale/sl/LC_MESSAGES/djangojs.po
dynamicforms/migrations/__init__.py
dynamicforms/mixins/__init__.py
dynamicforms/mixins/action.py
dynamicforms/mixins/color_field.py
dynamicforms/mixins/conditional_visibility.py
dynamicforms/mixins/enable_copy.py
dynamicforms/mixins/field_render.py
dynamicforms/mixins/file_field.py
dynamicforms/mixins/help_text.py
dynamicforms/mixins/implicit_hidden.py
dynamicforms/mixins/implicit_natural_date.py
dynamicforms/mixins/null_value.py
dynamicforms/mixins/password_field.py
dynamicforms/mixins/related_field_ajax.py
dynamicforms/mixins/rtf_field.py
dynamicforms/mixins/choice/__init__.py
dynamicforms/mixins/choice/allow_tags.py
dynamicforms/mixins/choice/null_choice.py
dynamicforms/mixins/choice/single_choice.py
dynamicforms/template_render/__init__.py
dynamicforms/template_render/layout.py
dynamicforms/template_render/renderer.py
dynamicforms/template_render/responsive_table_layout.py
dynamicforms/template_render/mixins/__init__.py
dynamicforms/template_render/mixins/base.py
dynamicforms/template_render/mixins/field.py
dynamicforms/template_render/mixins/listserializer.py
dynamicforms/template_render/mixins/render_mode_enum.py
dynamicforms/template_render/mixins/serializer.py
dynamicforms/template_render/mixins/serializer_filter.py
dynamicforms/template_render/mixins/serializer_render_actions.py
dynamicforms-0.81.2.dist-info/METADATA
dynamicforms-0.81.2.dist-info/WHEEL
dynamicforms-0.81.2.dist-info/licenses/LICENSE
dynamicforms-0.81.2.dist-info/RECORD
