Metadata-Version: 2.4
Name: dynamicforms
Version: 0.81.2
Summary: DyF performs all the visualisation & data entry of your DRF Serializers & ViewSets and adds some candy of its own
Project-URL: Homepage, https://github.com/velis74/DynamicForms
Project-URL: Repository, https://github.com/velis74/DynamicForms
Project-URL: Bug Tracker, https://github.com/velis74/DynamicForms/issues
Author-email: Jure Erznožnik <support@velis.si>
License: Proprietary
License-File: LICENSE
Classifier: Development Status :: 3 - Alpha
Classifier: Framework :: Django
Classifier: License :: Other/Proprietary License
Classifier: Operating System :: OS Independent
Classifier: Programming Language :: Python :: 3
Requires-Python: >=3.8
Requires-Dist: coreapi>=1.32
Requires-Dist: django-cors-headers
Requires-Dist: django-enumfields>=2.1.1
Requires-Dist: django-filter
Requires-Dist: django>=2
Requires-Dist: djangorestframework>=3.14
Requires-Dist: drf-spectacular
Requires-Dist: jsonschema
Requires-Dist: pillow
Requires-Dist: pytz
Requires-Dist: ruff
Requires-Dist: ruff-lsp
Requires-Dist: six
Requires-Dist: versio
